Recitation/Recitation-03/majority.v
module majority(A, Y);

  input [2:0]A;
  output Y;

  assign Y = (A[0] & A[1]) | (A[1] & A[2]) | (A[0] & A[2]);

endmodule

Recitation/Recitation-03/majority_tb.v
// Verilog test bench for E15 homework 5 problem 1.

`timescale 1ns/100ps
`include "majority.v"

module majority_tb;

   wire [2:0] A;
   wire       Y;
   integer k=0;

   assign A = k;
   majority the_circuit(A, Y);

   initial begin

      $dumpfile("majority.vcd");
      $dumpvars(0, majority_tb);

      for (k=0; k<8; k=k+1)
        #10 $display("done testing case %d", k);

      $finish;

   end 

endmodule

Recitation/Recitation-03/majority.vcd
$date
	Fri Sep 16 14:59:31 2022
$end
$version
	Icarus Verilog
$end
$timescale
	100ps
$end
$scope module majority_tb $end
$var wire 1 ! Y $end
$var wire 3 " A [2:0] $end
$var integer 32 # k [31:0] $end
$scope module the_circuit $end
$var wire 3 $ A [2:0] $end
$var wire 1 ! Y $end
$upscope $end
$upscope $end
$enddefinitions $end
#0
$dumpvars
b0 $
b0 #
b0 "
0!
$end
#100
b1 "
b1 $
b1 #
#200
b10 "
b10 $
b10 #
#300
1!
b11 "
b11 $
b11 #
#400
0!
b100 "
b100 $
b100 #
#500
1!
b101 "
b101 $
b101 #
#600
1!
b110 "
b110 $
b110 #
#700
b111 "
b111 $
b111 #
#800
0!
b0 "
b0 $
b1000 #
